{
  "type": "betterend:infusion",
  "catalysts": {
    "east": "minecraft:ender_eye",
    "north": "betterend:enchanted_petal",
    "north_east": "minecraft:lapis_lazuli",
    "north_west": "minecraft:lapis_lazuli",
    "south": "minecraft:heart_of_the_sea",
    "south_east": "minecraft:lapis_lazuli",
    "south_west": "minecraft:lapis_lazuli",
    "west": "minecraft:ender_eye"
  },
  "group": "enchantment",
  "input": "minecraft:book",
  "result": {
    "item": "minecraft:enchanted_book",
    "nbt": {
      "minecraft:stored_enchantments": {
        "minecraft:loyalty": 1
      }
    }
  },
  "time": 375
}